avocado/__init__.py
avocado/io.py
avocado/model.py
avocado/utils.py
avocado_epigenome-0.4.0.data/scripts/avocado-impute
avocado_epigenome-0.4.0.dist-info/LICENSE
avocado_epigenome-0.4.0.dist-info/METADATA
avocado_epigenome-0.4.0.dist-info/WHEEL
avocado_epigenome-0.4.0.dist-info/top_level.txt
avocado_epigenome-0.4.0.dist-info/RECORD
